flask_oasschema/__init__.py
flask_oasschema/flask_oasschema.py
Flask_OASSchema-0.9.14.dist-info/LICENSE
Flask_OASSchema-0.9.14.dist-info/METADATA
Flask_OASSchema-0.9.14.dist-info/WHEEL
Flask_OASSchema-0.9.14.dist-info/top_level.txt
Flask_OASSchema-0.9.14.dist-info/RECORD
