Metadata-Version: 2.1
Name: Flask-OASSchema
Version: 0.9.14
Summary: Flask extension for validating JSON requests
Home-page: https://github.com/IlyaSukhanov/flask-oasschema
Author: Ilya Sukhanov
Author-email: ilya@sukhanov.net
License: MIT
Platform: any
Classifier: Development Status :: 4 - Beta
Classifier: Environment :: Web Environment
Classifier: Intended Audience :: Developers
Classifier: License :: OSI Approved :: MIT License
Classifier: Operating System :: OS Independent
Classifier: Programming Language :: Python
Classifier: Topic :: Internet :: WWW/HTTP :: Dynamic Content
Classifier: Topic :: Software Development :: Libraries :: Python Modules
Requires-Dist: Flask (>=0.9)
Requires-Dist: jsonschema (>=1.1.0)
Requires-Dist: future (>=0.16.0)
Requires-Dist: jsonref (>=0.2)
Provides-Extra: testing
Requires-Dist: flake8 ; extra == 'testing'
Requires-Dist: pytest ; extra == 'testing'
Requires-Dist: pyflakes ; extra == 'testing'
Requires-Dist: pytest-cov ; extra == 'testing'
Requires-Dist: coverage ; extra == 'testing'
Requires-Dist: wheel ; extra == 'testing'
Requires-Dist: twine ; extra == 'testing'
Requires-Dist: black ; extra == 'testing'
